.editorconfig
.gitignore
.gitlab-ci.yml
README.rst
publish.settings.sh
publish.sh
pyproject.toml
tsconfig.json
.idea/modules.xml
.idea/peek-plugin-eventdb.iml
.idea/inspectionProfiles/Project_Default.xml
.idea/inspectionProfiles/profiles_settings.xml
peek_plugin_eventdb/__init__.py
peek_plugin_eventdb/plugin_package.json
peek_plugin_eventdb.egg-info/PKG-INFO
peek_plugin_eventdb.egg-info/SOURCES.txt
peek_plugin_eventdb.egg-info/dependency_links.txt
peek_plugin_eventdb.egg-info/requires.txt
peek_plugin_eventdb.egg-info/top_level.txt
peek_plugin_eventdb/_private/PluginNames.py
peek_plugin_eventdb/_private/PluginNamesTest.py
peek_plugin_eventdb/_private/__init__.py
peek_plugin_eventdb/_private/alembic.ini
peek_plugin_eventdb/_private/admin-app/PluginNames.ts
peek_plugin_eventdb/_private/admin-app/eventdb.module.ts
peek_plugin_eventdb/_private/admin-app/components/edit-property-table/edit.component.html
peek_plugin_eventdb/_private/admin-app/components/edit-property-table/edit.component.scss
peek_plugin_eventdb/_private/admin-app/components/edit-property-table/edit.component.ts
peek_plugin_eventdb/_private/admin-app/components/edit-setting-table/edit.component.html
peek_plugin_eventdb/_private/admin-app/components/edit-setting-table/edit.component.scss
peek_plugin_eventdb/_private/admin-app/components/edit-setting-table/edit.component.ts
peek_plugin_eventdb/_private/admin-app/components/eventdb-page/eventdb-page.component.html
peek_plugin_eventdb/_private/admin-app/components/eventdb-page/eventdb-page.component.scss
peek_plugin_eventdb/_private/admin-app/components/eventdb-page/eventdb-page.component.ts
peek_plugin_eventdb/_private/admin-app/components/status/status.component.html
peek_plugin_eventdb/_private/admin-app/components/status/status.component.scss
peek_plugin_eventdb/_private/admin-app/components/status/status.component.ts
peek_plugin_eventdb/_private/admin-app/tuples/AdminStatusTuple.ts
peek_plugin_eventdb/_private/admin-app/tuples/EventDBModelSetTableTuple.ts
peek_plugin_eventdb/_private/admin-app/tuples/EventDBPropertyTableTuple.ts
peek_plugin_eventdb/_private/admin-app/tuples/EventDBPropertyValueTableTuple.ts
