Metadata-Version: 2.4
Name: peek-plugin-eventdb
Version: 5.0.4
Summary: Peek Plugin EventDB - storage of the historical and current events and alarms
Author-email: Synerty <contact@synerty.com>
Project-URL: Homepage, https://github.com/Synerty/peek-plugin-eventdb
Keywords: Peek,Python,Platform,synerty
Requires-Dist: peek-plugin-base==5.0.4
